quicklooper/__init__.py
quicklooper/looper.py
quicklooper-1.0.0.dist-info/LICENSE
quicklooper-1.0.0.dist-info/METADATA
quicklooper-1.0.0.dist-info/WHEEL
quicklooper-1.0.0.dist-info/top_level.txt
quicklooper-1.0.0.dist-info/RECORD
