Metadata-Version: 2.1
Name: quicklooper
Version: 1.0.0
Summary: Simple polling-style loop running in separate thread
Home-page: https://github.com/deuxglaces/quicklooper
Author: Deux Glaces
License: MIT
Platform: UNKNOWN
Classifier: License :: OSI Approved :: MIT License
Classifier: Programming Language :: Python :: 3
Classifier: Programming Language :: Python :: 3.7
Classifier: Programming Language :: Python :: 3.8
Classifier: Programming Language :: Python :: 3.9
Classifier: Programming Language :: Python :: 3.10
License-File: LICENSE
